CHANGES.rst
DESCRIPTION.rst
LICENSE
MANIFEST.in
README.md
setup.py
src/wai/json/__init__.py
src/wai/json/error/_JSONError.py
src/wai/json/error/_JSONPropertyError.py
src/wai/json/error/_JSONSchemaError.py
src/wai/json/error/_JSONSerialisationError.py
src/wai/json/error/_JSONValidationError.py
src/wai/json/error/_OfPropertySelectionError.py
src/wai/json/error/_OptionalDisallowed.py
src/wai/json/error/_RequiredDisallowed.py
src/wai/json/error/_SchemaDefinitionRedefined.py
src/wai/json/error/__init__.py
src/wai/json/object/_JSONObject.py
src/wai/json/object/_StrictJSONObject.py
src/wai/json/object/__init__.py
src/wai/json/object/_typing.py
src/wai/json/object/property/_AllOfProperty.py
src/wai/json/object/property/_AnyOfProperty.py
src/wai/json/object/property/_ArrayProperty.py
src/wai/json/object/property/_BoolProperty.py
src/wai/json/object/property/_ConstantProperty.py
src/wai/json/object/property/_EnumProperty.py
src/wai/json/object/property/_JSONObjectProperty.py
src/wai/json/object/property/_MapProperty.py
src/wai/json/object/property/_NumberProperty.py
src/wai/json/object/property/_OfProperty.py
src/wai/json/object/property/_OneOfProperty.py
src/wai/json/object/property/_Property.py
src/wai/json/object/property/_ProxyProperty.py
src/wai/json/object/property/_RawProperty.py
src/wai/json/object/property/_StringProperty.py
src/wai/json/object/property/__init__.py
src/wai/json/object/property/proxies/_ArrayProxy.py
src/wai/json/object/property/proxies/_MapProxy.py
src/wai/json/object/property/proxies/__init__.py
src/wai/json/raw/__init__.py
src/wai/json/raw/_deep_copy.py
src/wai/json/raw/_dynamic.py
src/wai/json/raw/_typing.py
src/wai/json/schema/__init__.py
src/wai/json/schema/_definitions.py
src/wai/json/schema/_dynamic.py
src/wai/json/schema/_static.py
src/wai/json/schema/_typing.py
src/wai/json/schema/constants.py
src/wai/json/serialise/_JSONBiserialisable.py
src/wai/json/serialise/_JSONDeserialisable.py
src/wai/json/serialise/_JSONSerialisable.py
src/wai_json.egg-info/PKG-INFO
src/wai_json.egg-info/SOURCES.txt
src/wai_json.egg-info/dependency_links.txt
src/wai_json.egg-info/requires.txt
src/wai_json.egg-info/top_level.txt
