Metadata-Version: 2.1
Name: wai-json
Version: 0.0.6
Summary: Python library for working with JSON and JSON schema.
Home-page: https://github.com/waikato-datamining/wai-json
Author: Corey Sterling
Author-email: coreytsterling@gmail.com
License: MIT
Classifier: Development Status :: 4 - Beta
Classifier: License :: OSI Approved :: MIT License
Classifier: Topic :: Scientific/Engineering :: Mathematics
Classifier: Programming Language :: Python :: 3
License-File: LICENSE
